wexample_workdirs/__init__.py
wexample_workdirs/utils/__init__.py
wexample_workdirs/utils/workdir.py
wexample_workdirs-0.0.2.dist-info/METADATA
wexample_workdirs-0.0.2.dist-info/WHEEL
wexample_workdirs-0.0.2.dist-info/top_level.txt
wexample_workdirs-0.0.2.dist-info/RECORD
